teleport_ansible/inventory.py
teleport_ansible/meta.py
teleport_ansible-0.0.1.dist-info/LICENSE
teleport_ansible-0.0.1.dist-info/METADATA
teleport_ansible-0.0.1.dist-info/WHEEL
teleport_ansible-0.0.1.dist-info/entry_points.txt
teleport_ansible-0.0.1.dist-info/top_level.txt
teleport_ansible-0.0.1.dist-info/RECORD
