Metadata-Version: 2.1
Name: teleport-ansible
Version: 0.0.1
Summary: Teleport driven ansible inventory script.
Home-page: https://github.com/cloudnull/teleport-ansible
Author: Kevin Carter
Author-email: kevin@cloudnull.com
Project-URL: Bug Tracker, https://github.com/cloudnull/teleport-ansible/issues
Classifier: Development Status :: 5 - Production/Stable
Classifier: Intended Audience :: Information Technology
Classifier: Intended Audience :: System Administrators
Classifier: Intended Audience :: Developers
Classifier: Operating System :: OS Independent
Classifier: Programming Language :: Python :: 3.8
Classifier: Topic :: Utilities
Classifier: Topic :: Software Development :: Libraries :: Python Modules
Requires-Python: >=3.6
License-File: LICENSE
